georgeforge/__init__.py
georgeforge/admin.py
georgeforge/app_settings.py
georgeforge/apps.py
georgeforge/auth_hooks.py
georgeforge/forms.py
georgeforge/models.py
georgeforge/tasks.py
georgeforge/urls.py
georgeforge/views.py
georgeforge/locale/.gitkeep
georgeforge/management/commands/georgeforge_eveuniverse_load.py
georgeforge/migrations/0001_squashed_0020_alter_order_deposit_alter_order_paid_and_more.py
georgeforge/migrations/0021_alter_order_deliverysystem.py
georgeforge/migrations/0022_add_order_cart_session_id.py
georgeforge/migrations/0023_remove_cart_session_id_unique.py
georgeforge/migrations/0024_add_order_estimated_delivery_date.py
georgeforge/migrations/0025_alter_estimated_delivery_date_to_string.py
georgeforge/migrations/0026_remove_order_on_behalf_of.py
georgeforge/migrations/0027_alter_order_estimated_delivery_date.py
georgeforge/migrations/__init__.py
georgeforge/static/georgeforge/.gitkeep
georgeforge/static/georgeforge/css/itemOverlay.css
georgeforge/static/georgeforge/img/14.png
georgeforge/static/georgeforge/img/2.png
georgeforge/static/georgeforge/img/3.png
georgeforge/static/georgeforge/img/4.png
georgeforge/static/georgeforge/img/5.png
georgeforge/static/georgeforge/img/6.png
georgeforge/static/georgeforge/img/96.png
georgeforge/static/georgeforge/img/97.png
georgeforge/static/georgeforge/img/98.png
georgeforge/static/georgeforge/img/99.png
georgeforge/static/georgeforge/js/cart.js
georgeforge/static/georgeforge/js/store-search.js
georgeforge/static/georgeforge/js/store-table.js
georgeforge/templates/georgeforge/base.html
georgeforge/templates/georgeforge/partials/discord_notice.html
georgeforge/templates/georgeforge/partials/order_pips.css.html
georgeforge/templates/georgeforge/partials/order_table_editable.css.html
georgeforge/templates/georgeforge/partials/order_table_editable.html
georgeforge/templates/georgeforge/partials/order_table_header.html
georgeforge/templates/georgeforge/partials/order_table_javascript.html
allianceauth_georgeforge-0.3.11.dist-info/METADATA
allianceauth_georgeforge-0.3.11.dist-info/WHEEL
allianceauth_georgeforge-0.3.11.dist-info/licenses/LICENSE
allianceauth_georgeforge-0.3.11.dist-info/RECORD
