Metadata-Version: 2.4
Name: allianceauth-georgeforge
Version: 0.3.11
License:                     GNU GENERAL PUBLIC LICENSE
License-File: LICENSE
Keywords: allianceauth
Classifier: Environment :: Web Environment
Classifier: Framework :: Django
Classifier: Framework :: Django :: 4.2
Classifier: Intended Audience :: Developers
Classifier: License :: OSI Approved :: GNU General Public License v3 (GPLv3)
Classifier: Operating System :: OS Independent
Classifier: Programming Language :: Python
Classifier: Programming Language :: Python :: 3 :: Only
Classifier: Programming Language :: Python :: 3.10
Classifier: Programming Language :: Python :: 3.11
Classifier: Programming Language :: Python :: 3.12
Classifier: Topic :: Internet :: WWW/HTTP
Classifier: Topic :: Internet :: WWW/HTTP :: Dynamic Content
Requires-Python: >=3.10
Requires-Dist: allianceauth<5,>=4
Requires-Dist: django-eveuniverse<2,>=1
Provides-Extra: dev
Requires-Dist: django-stubs; extra == 'dev'
Provides-Extra: discord
Requires-Dist: allianceauth-discordbot<5,>=4; extra == 'discord'
Requires-Dist: py-cord<3,>=2; extra == 'discord'
Provides-Extra: webhook
Requires-Dist: py-cord<3,>=2; extra == 'webhook'
